{"client_name": "", "mobile": "", "company": "", "gst": "", "address": "", "items": [{"name": "C3-230", "price": "120000", "quantity": 1, "discount": 0, "image": "/static/images/Kohler_PriceBook_Nov_p6_i1.jpg", "rawText": "C3-230\nElectronic seat cover with cleansing functionality and remote in white\nK-4108IN-0\nMRP ` 1,20,000.00\n(incl of all taxes)"}], "discount_percent": 0, "gst_rate": 18, "subtotal": 120000, "discount_amount": 0, "taxable_amount": 120000, "gst_amount": 21600, "grand_total": 141600}